Genskew_univiecube/__init__.py
Genskew_univiecube-0.1.3.dist-info/LICENSE
Genskew_univiecube-0.1.3.dist-info/METADATA
Genskew_univiecube-0.1.3.dist-info/WHEEL
Genskew_univiecube-0.1.3.dist-info/top_level.txt
Genskew_univiecube-0.1.3.dist-info/RECORD
