Metadata-Version: 2.1
Name: Genskew-univiecube
Version: 0.1.3
Summary: A program that calculates the skew of two selectable nucleotides for a genome sequence in FASTA or GenBank format.
Home-page: https://genskew.csb.univie.ac.at/library_documentation
Author: Thomas Rattei, Julius Krämer
License: Creative Commons
Classifier: Programming Language :: Python :: 3
Classifier: Operating System :: OS Independent
Requires-Python: >=3.6
License-File: LICENSE
Requires-Dist: matplotlib
Requires-Dist: Biopython
Requires-Dist: argparse
Requires-Dist: Genskew-cc
Requires-Dist: GUIskew
Requires-Dist: numpy
